oidia/__init__.py
oidia/__main__.py
oidia/app.py
oidia/py.typed
oidia/screens/__init__.py
oidia/screens/main.py
oidia/widgets/__init__.py
oidia/widgets/streakline.py
oidia/widgets/streaks.py
oidia/widgets/timeline.py
oidia/widgets/title_input.py
oidia-0.6.1.dist-info/LICENSE
oidia-0.6.1.dist-info/METADATA
oidia-0.6.1.dist-info/WHEEL
oidia-0.6.1.dist-info/entry_points.txt
oidia-0.6.1.dist-info/top_level.txt
oidia-0.6.1.dist-info/RECORD
